stop_sequencer/__init__.py
stop_sequencer/stop_sequencer.py
stop_sequencer/stopping_criteria.py
tests/__init__.py
tests/test.py
stop_sequencer-1.2.0.dist-info/METADATA
stop_sequencer-1.2.0.dist-info/WHEEL
stop_sequencer-1.2.0.dist-info/top_level.txt
stop_sequencer-1.2.0.dist-info/RECORD
