Metadata-Version: 2.1
Name: stop-sequencer
Version: 1.2.0
Summary: Implementation of stop sequencer for Huggingface Transformers
Home-page: https://github.com/hyunwoongko/stop-sequencer
Author: Hyunwoong Ko
Author-email: gusdnd852@naver.com
License: UNKNOWN
Platform: UNKNOWN
Classifier: Programming Language :: Python :: 3
Classifier: Programming Language :: Python :: 3.2
Classifier: Programming Language :: Python :: 3.3
Classifier: Programming Language :: Python :: 3.4
Classifier: Programming Language :: Python :: 3.5
Classifier: Programming Language :: Python :: 3.6
Classifier: Programming Language :: Python :: 3.7
Classifier: Programming Language :: Python :: 3.8
Classifier: Programming Language :: Python :: 3.9
Classifier: Topic :: Scientific/Engineering :: Artificial Intelligence
Classifier: Topic :: Software Development :: Libraries
Requires-Python: >=3
Requires-Dist: transformers (>=4<4.3.0)
Requires-Dist: torch
